wizmusic/__init__.py
wizmusic/client.py
wizmusic/player.py
wizmusic/utils.py
wizmusic/wiz.py
wizmusic-0.1.2.dist-info/entry_points.txt
wizmusic-0.1.2.dist-info/WHEEL
wizmusic-0.1.2.dist-info/METADATA
wizmusic-0.1.2.dist-info/RECORD
